<?xml version="1.0" encoding="UTF-8"?>
<root>
    <doclet-version-NOT-library-version>1.02</doclet-version-NOT-library-version>
    <class>
        <name>jWebCam.JWebCam</name>
        <shortname>jWebCam</shortname>
        <owner>process</owner>
        <method>
            <name>pause</name>
            <comment></comment>
            <returntype>void</returntype>
        </method>
        <method>
            <name>Initialize</name>
            <comment></comment>
            <returntype>void</returntype>
            <parameter>
                <name>canvas</name>
                <type>javafx.scene.canvas.Canvas</type>
            </parameter>
            <parameter>
                <name>device</name>
                <type>java.lang.String</type>
            </parameter>
            <parameter>
                <name>media</name>
                <type>java.lang.String</type>
            </parameter>
        </method>
        <method>
            <name>grab</name>
            <comment></comment>
            <returntype>void</returntype>
            <parameter>
                <name>filename</name>
                <type>java.lang.String</type>
            </parameter>
        </method>
        <method>
            <name>stop</name>
            <comment></comment>
            <returntype>void</returntype>
        </method>
        <method>
            <name>resume</name>
            <comment></comment>
            <returntype>void</returntype>
        </method>
        <method>
            <name>release</name>
            <comment></comment>
            <returntype>void</returntype>
        </method>
    </class>
    <version>0.01</version>
    <author>Daestrum</author>
</root>
