<?xml version="1.0" encoding="UTF-8"?>
<root>
    <doclet-version-NOT-library-version>1.04</doclet-version-NOT-library-version>
    <class>
        <name>com.aurelhubert.ahbottomnavigation.AHBottom</name>
        <shortname>MaterialBottomNavigation</shortname>
        <objectwrapper>com.aurelhubert.ahbottomnavigation.AHBottomNavigation</objectwrapper>
        <owner>activity</owner>
        <event>onpositionchange(position as int)</event>
        <event>ontabselected(position as int,wasSelected as boolean)</event>
        <method>
            <name>SetColoredModeColors</name>
            <comment>Set the colors used when the bottom bar uses the colored mode
colorActive: The active color
colorInactive: The inactive color</comment>
            <returntype>void</returntype>
            <parameter>
                <name>colorActive</name>
                <type>int</type>
            </parameter>
            <parameter>
                <name>colorInactive</name>
                <type>int</type>
            </parameter>
        </method>
        <method>
            <name>RemoveView</name>
            <comment></comment>
            <returntype>void</returntype>
        </method>
        <method>
            <name>AddItem</name>
            <comment>Add an item</comment>
            <returntype>void</returntype>
            <parameter>
                <name>item</name>
                <type>com.aurelhubert.ahbottomnavigation.AHBottomNavigationItem</type>
            </parameter>
        </method>
        <method>
            <name>SetBackgroundImage</name>
            <comment></comment>
            <returntype>void</returntype>
            <parameter>
                <name>arg0</name>
                <type>android.graphics.Bitmap</type>
            </parameter>
        </method>
        <method>
            <name>SetColored</name>
            <comment>Set if the Bottom Navigation is colored</comment>
            <returntype>void</returntype>
            <parameter>
                <name>colored</name>
                <type>boolean</type>
            </parameter>
        </method>
        <method>
            <name>SetTranslucentNavigationEnabled</name>
            <comment>Set the translucent navigation value</comment>
            <returntype>void</returntype>
            <parameter>
                <name>translucentNavigationEnabled</name>
                <type>boolean</type>
            </parameter>
        </method>
        <method>
            <name>SetNotificationBackground</name>
            <comment>Set notification background resource
drawable: Drawable</comment>
            <returntype>void</returntype>
            <parameter>
                <name>drawable</name>
                <type>android.graphics.drawable.Drawable</type>
            </parameter>
        </method>
        <method>
            <name>SetNotification</name>
            <comment>Set notification text
title: String
itemPosition: int</comment>
            <returntype>void</returntype>
            <parameter>
                <name>title</name>
                <type>java.lang.String</type>
            </parameter>
            <parameter>
                <name>itemPosition</name>
                <type>int</type>
            </parameter>
        </method>
        <method>
            <name>IsInitialized</name>
            <comment></comment>
            <returntype>boolean</returntype>
        </method>
        <method>
            <name>Initialize</name>
            <comment></comment>
            <returntype>void</returntype>
            <parameter>
                <name>bA</name>
                <type>anywheresoftware.b4a.BA</type>
            </parameter>
            <parameter>
                <name>EventName</name>
                <type>java.lang.String</type>
            </parameter>
        </method>
        <method>
            <name>SetInactiveColor</name>
            <comment>Set the inactive color (used when the view contains 3 items)
inactiveColor: The inactive color</comment>
            <returntype>void</returntype>
            <parameter>
                <name>inactiveColor</name>
                <type>int</type>
            </parameter>
        </method>
        <method>
            <name>SetTitleState</name>
            <comment>Sets the title state for each tab
 SHOW_WHEN_ACTIVE: when a tab is focused
 ALWAYS_SHOW: show regardless of which tab is in focus
 ALWAYS_HIDE: never show tab titles
 Note: Always showing the title is against Material Design guidelines
titleState: TitleState</comment>
            <returntype>void</returntype>
            <parameter>
                <name>titleState</name>
                <type EnumType="true">com.aurelhubert.ahbottomnavigation.AHBottomNavigation.TitleState</type>
            </parameter>
        </method>
        <method>
            <name>HideBottomNavigation</name>
            <comment>Hide Bottom Navigation with animation</comment>
            <returntype>void</returntype>
        </method>
        <method>
            <name>Invalidate</name>
            <comment></comment>
            <returntype>void</returntype>
        </method>
        <method>
            <name>SetLayout</name>
            <comment></comment>
            <returntype>void</returntype>
            <parameter>
                <name>arg0</name>
                <type Pixel="true">int</type>
            </parameter>
            <parameter>
                <name>arg1</name>
                <type Pixel="true">int</type>
            </parameter>
            <parameter>
                <name>arg2</name>
                <type Pixel="true">int</type>
            </parameter>
            <parameter>
                <name>arg3</name>
                <type Pixel="true">int</type>
            </parameter>
        </method>
        <method>
            <name>DesignerCreateView</name>
            <comment></comment>
            <returntype>void</returntype>
            <parameter>
                <name>panelWrapper</name>
                <type>anywheresoftware.b4a.objects.PanelWrapper</type>
            </parameter>
            <parameter>
                <name>labelWrapper</name>
                <type>anywheresoftware.b4a.objects.LabelWrapper</type>
            </parameter>
            <parameter>
                <name>map</name>
                <type>anywheresoftware.b4a.objects.collections.Map</type>
            </parameter>
        </method>
        <method>
            <name>AddToParent</name>
            <comment></comment>
            <returntype>void</returntype>
            <parameter>
                <name>viewGroup</name>
                <type>android.view.ViewGroup</type>
            </parameter>
            <parameter>
                <name>n</name>
                <type Pixel="true">int</type>
            </parameter>
            <parameter>
                <name>n2</name>
                <type Pixel="true">int</type>
            </parameter>
            <parameter>
                <name>n3</name>
                <type Pixel="true">int</type>
            </parameter>
            <parameter>
                <name>n4</name>
                <type Pixel="true">int</type>
            </parameter>
        </method>
        <method>
            <name>HideBottomNavigation2</name>
            <comment>Hide Bottom Navigation with or without animation
withAnimation: Boolean</comment>
            <returntype>void</returntype>
            <parameter>
                <name>withAnimation</name>
                <type>boolean</type>
            </parameter>
        </method>
        <method>
            <name>AddItems2</name>
            <comment>Add all items</comment>
            <returntype>void</returntype>
            <parameter>
                <name>items</name>
                <type>java.util.List</type>
            </parameter>
        </method>
        <method>
            <name>RestoreBottomNavigation</name>
            <comment>Restore Bottom Navigation with animation</comment>
            <returntype>void</returntype>
        </method>
        <method>
            <name>RequestFocus</name>
            <comment></comment>
            <returntype>boolean</returntype>
        </method>
        <method>
            <name>BringToFront</name>
            <comment></comment>
            <returntype>void</returntype>
        </method>
        <method>
            <name>SetCurrentItem2</name>
            <comment>Set the current item
position: int: item position
useCallback: boolean: use or not the callback</comment>
            <returntype>void</returntype>
            <parameter>
                <name>position</name>
                <type>int</type>
            </parameter>
            <parameter>
                <name>useCallback</name>
                <type>boolean</type>
            </parameter>
        </method>
        <method>
            <name>SetNotificationMarginLeft</name>
            <comment>Set the notification margin left
activeMargin: 
inactiveMargin: </comment>
            <returntype>void</returntype>
            <parameter>
                <name>activeMargin</name>
                <type>int</type>
            </parameter>
            <parameter>
                <name>inactiveMargin</name>
                <type>int</type>
            </parameter>
        </method>
        <method>
            <name>SetCurrentItem</name>
            <comment>Set the current item
position: int: position</comment>
            <returntype>void</returntype>
            <parameter>
                <name>position</name>
                <type>int</type>
            </parameter>
        </method>
        <method>
            <name>SetTitleTypeface</name>
            <comment>Set notification typeface
typeface: Typeface</comment>
            <returntype>void</returntype>
            <parameter>
                <name>typeface</name>
                <type>android.graphics.Typeface</type>
            </parameter>
        </method>
        <method>
            <name>SetAccentColor</name>
            <comment>Set the accent color (used when the view contains 3 items)
accentColor: The new accent color</comment>
            <returntype>void</returntype>
            <parameter>
                <name>accentColor</name>
                <type>int</type>
            </parameter>
        </method>
        <method>
            <name>SetUseElevation</name>
            <comment>Activate or not the elevation
useElevation: boolean</comment>
            <returntype>void</returntype>
            <parameter>
                <name>useElevation</name>
                <type>boolean</type>
            </parameter>
        </method>
        <method>
            <name>Invalidate3</name>
            <comment></comment>
            <returntype>void</returntype>
            <parameter>
                <name>arg0</name>
                <type>int</type>
            </parameter>
            <parameter>
                <name>arg1</name>
                <type>int</type>
            </parameter>
            <parameter>
                <name>arg2</name>
                <type>int</type>
            </parameter>
            <parameter>
                <name>arg3</name>
                <type>int</type>
            </parameter>
        </method>
        <method>
            <name>SetNotificationBackgroundColor</name>
            <comment>Set notification background color
color: int</comment>
            <returntype>void</returntype>
            <parameter>
                <name>color</name>
                <type>int</type>
            </parameter>
        </method>
        <method>
            <name>Invalidate2</name>
            <comment></comment>
            <returntype>void</returntype>
            <parameter>
                <name>arg0</name>
                <type>android.graphics.Rect</type>
            </parameter>
        </method>
        <method>
            <name>SetBehaviorTranslationEnabled</name>
            <comment>Set the behavior translation value
behaviorTranslationEnabled: boolean for the state</comment>
            <returntype>void</returntype>
            <parameter>
                <name>behaviorTranslationEnabled</name>
                <type>boolean</type>
            </parameter>
        </method>
        <method>
            <name>SetNotificationTextColor</name>
            <comment>Set notification text color
textColor: int</comment>
            <returntype>void</returntype>
            <parameter>
                <name>textColor</name>
                <type>int</type>
            </parameter>
        </method>
        <method>
            <name>Refresh</name>
            <comment>Refresh the AHBottomView</comment>
            <returntype>void</returntype>
        </method>
        <method>
            <name>RemoveItemAtIndex</name>
            <comment>Remove an item at the given index</comment>
            <returntype>void</returntype>
            <parameter>
                <name>index</name>
                <type>int</type>
            </parameter>
        </method>
        <method>
            <name>SetTitleTextSize</name>
            <comment>Set title text size
activeSize: 
inactiveSize: </comment>
            <returntype>void</returntype>
            <parameter>
                <name>activeSize</name>
                <type>float</type>
            </parameter>
            <parameter>
                <name>inactiveSize</name>
                <type>float</type>
            </parameter>
        </method>
        <method>
            <name>SetDefaultBackgroundColor</name>
            <comment>Set the bottom navigation background color
defaultBackgroundColor: The bottom navigation background color</comment>
            <returntype>void</returntype>
            <parameter>
                <name>defaultBackgroundColor</name>
                <type>int</type>
            </parameter>
        </method>
        <method>
            <name>RemoveAllItems</name>
            <comment>Remove all items</comment>
            <returntype>void</returntype>
        </method>
        <method>
            <name>SetColorAnimated</name>
            <comment></comment>
            <returntype>void</returntype>
            <parameter>
                <name>arg0</name>
                <type>int</type>
            </parameter>
            <parameter>
                <name>arg1</name>
                <type>int</type>
            </parameter>
            <parameter>
                <name>arg2</name>
                <type>int</type>
            </parameter>
        </method>
        <method>
            <name>SetForceTint</name>
            <comment>Set the force tint value
 If forceTint = true, the tint is made with drawable.setColorFilter(color, PorterDuff.Mode.SRC_IN);
forceTint: Boolean</comment>
            <returntype>void</returntype>
            <parameter>
                <name>forceTint</name>
                <type>boolean</type>
            </parameter>
        </method>
        <method>
            <name>SetNotificationTypeface</name>
            <comment>Set notification typeface
typeface: Typeface</comment>
            <returntype>void</returntype>
            <parameter>
                <name>typeface</name>
                <type>android.graphics.Typeface</type>
            </parameter>
        </method>
        <method>
            <name>SetLayoutAnimated</name>
            <comment></comment>
            <returntype>void</returntype>
            <parameter>
                <name>arg0</name>
                <type>int</type>
            </parameter>
            <parameter>
                <name>arg1</name>
                <type Pixel="true">int</type>
            </parameter>
            <parameter>
                <name>arg2</name>
                <type Pixel="true">int</type>
            </parameter>
            <parameter>
                <name>arg3</name>
                <type Pixel="true">int</type>
            </parameter>
            <parameter>
                <name>arg4</name>
                <type Pixel="true">int</type>
            </parameter>
        </method>
        <method>
            <name>SetSelectedBackgroundVisible</name>
            <comment>Set selected background visibility</comment>
            <returntype>void</returntype>
            <parameter>
                <name>visible</name>
                <type>boolean</type>
            </parameter>
        </method>
        <method>
            <name>SetVisibleAnimated</name>
            <comment></comment>
            <returntype>void</returntype>
            <parameter>
                <name>arg0</name>
                <type>int</type>
            </parameter>
            <parameter>
                <name>arg1</name>
                <type>boolean</type>
            </parameter>
        </method>
        <method>
            <name>SetUseElevation2</name>
            <comment>Activate or not the elevation, and set the value
useElevation: boolean
elevation: float</comment>
            <returntype>void</returntype>
            <parameter>
                <name>useElevation</name>
                <type>boolean</type>
            </parameter>
            <parameter>
                <name>elevation</name>
                <type>float</type>
            </parameter>
        </method>
        <method>
            <name>SendToBack</name>
            <comment></comment>
            <returntype>void</returntype>
        </method>
        <method>
            <name>RestoreBottomNavigation2</name>
            <comment>Restore Bottom Navigation with or without animation
withAnimation: Boolean</comment>
            <returntype>void</returntype>
            <parameter>
                <name>withAnimation</name>
                <type>boolean</type>
            </parameter>
        </method>
        <property>
            <name>Enabled</name>
            <returntype>boolean</returntype>
            <parameter>
                <name>arg0</name>
                <type>boolean</type>
            </parameter>
            <comment></comment>
        </property>
        <property>
            <name>Parent</name>
            <returntype>java.lang.Object</returntype>
            <comment></comment>
        </property>
        <property>
            <name>Visible</name>
            <returntype>boolean</returntype>
            <parameter>
                <name>arg0</name>
                <type>boolean</type>
            </parameter>
            <comment></comment>
        </property>
        <property>
            <name>Tag</name>
            <returntype>java.lang.Object</returntype>
            <parameter>
                <name>arg0</name>
                <type>java.lang.Object</type>
            </parameter>
            <comment></comment>
        </property>
        <property>
            <name>Height</name>
            <returntype>int</returntype>
            <parameter>
                <name>arg0</name>
                <type Pixel="true">int</type>
            </parameter>
            <comment></comment>
        </property>
        <property>
            <name>Background</name>
            <returntype>android.graphics.drawable.Drawable</returntype>
            <parameter>
                <name>arg0</name>
                <type>android.graphics.drawable.Drawable</type>
            </parameter>
            <comment></comment>
        </property>
        <property>
            <name>Width</name>
            <returntype>int</returntype>
            <parameter>
                <name>arg0</name>
                <type Pixel="true">int</type>
            </parameter>
            <comment></comment>
        </property>
        <property>
            <name>Color</name>
            <parameter>
                <name>arg0</name>
                <type>int</type>
            </parameter>
            <comment></comment>
        </property>
        <field>
            <name>TitleState_ALWAYS_SHOW</name>
            <comment></comment>
            <returntype EnumType="true">com.aurelhubert.ahbottomnavigation.AHBottomNavigation.TitleState</returntype>
        </field>
        <field>
            <name>ba</name>
            <comment></comment>
            <returntype>anywheresoftware.b4a.BA</returntype>
        </field>
        <field>
            <name>TitleState_SHOW_WHEN_ACTIVE</name>
            <comment></comment>
            <returntype EnumType="true">com.aurelhubert.ahbottomnavigation.AHBottomNavigation.TitleState</returntype>
        </field>
        <field>
            <name>TitleState_ALWAYS_HIDE</name>
            <comment></comment>
            <returntype EnumType="true">com.aurelhubert.ahbottomnavigation.AHBottomNavigation.TitleState</returntype>
        </field>
    </class>
    <class>
        <name>com.aurelhubert.ahbottomnavigation.AHBottom.Item</name>
        <shortname>BottomNavigationItem</shortname>
        <objectwrapper>com.aurelhubert.ahbottomnavigation.AHBottomNavigationItem</objectwrapper>
        <owner>process</owner>
        <method>
            <name>Initialize</name>
            <comment>Constructor
title: String
drawable: Drawable
color: Color</comment>
            <returntype>void</returntype>
            <parameter>
                <name>title</name>
                <type>java.lang.String</type>
            </parameter>
            <parameter>
                <name>drawable</name>
                <type>android.graphics.drawable.Drawable</type>
            </parameter>
            <parameter>
                <name>color</name>
                <type>int</type>
            </parameter>
        </method>
        <method>
            <name>IsInitialized</name>
            <comment></comment>
            <returntype>boolean</returntype>
        </method>
    </class>
    <class>
        <name>com.aurelhubert.ahbottomnavigation.AHBottom.AHFAB</name>
        <shortname>FloatingActionButton</shortname>
        <objectwrapper>net.melnykov.fab.FloatingActionButton</objectwrapper>
        <owner>process</owner>
        <event>onclick</event>
        <event>onlongclick</event>
        <method>
            <name>RequestFocus</name>
            <comment></comment>
            <returntype>boolean</returntype>
        </method>
        <method>
            <name>BringToFront</name>
            <comment></comment>
            <returntype>void</returntype>
        </method>
        <method>
            <name>SetColorPressed</name>
            <comment></comment>
            <returntype>void</returntype>
            <parameter>
                <name>color</name>
                <type>int</type>
            </parameter>
        </method>
        <method>
            <name>SetShadow</name>
            <comment></comment>
            <returntype>void</returntype>
            <parameter>
                <name>shadow</name>
                <type>boolean</type>
            </parameter>
        </method>
        <method>
            <name>RemoveView</name>
            <comment></comment>
            <returntype>void</returntype>
        </method>
        <method>
            <name>SetBackgroundImage</name>
            <comment></comment>
            <returntype>void</returntype>
            <parameter>
                <name>arg0</name>
                <type>android.graphics.Bitmap</type>
            </parameter>
        </method>
        <method>
            <name>Hide2</name>
            <comment></comment>
            <returntype>void</returntype>
            <parameter>
                <name>animate</name>
                <type>boolean</type>
            </parameter>
        </method>
        <method>
            <name>SetColorNormal</name>
            <comment></comment>
            <returntype>void</returntype>
            <parameter>
                <name>color</name>
                <type>int</type>
            </parameter>
        </method>
        <method>
            <name>Invalidate3</name>
            <comment></comment>
            <returntype>void</returntype>
            <parameter>
                <name>arg0</name>
                <type>int</type>
            </parameter>
            <parameter>
                <name>arg1</name>
                <type>int</type>
            </parameter>
            <parameter>
                <name>arg2</name>
                <type>int</type>
            </parameter>
            <parameter>
                <name>arg3</name>
                <type>int</type>
            </parameter>
        </method>
        <method>
            <name>Hide</name>
            <comment></comment>
            <returntype>void</returntype>
        </method>
        <method>
            <name>IsVisible</name>
            <comment></comment>
            <returntype>boolean</returntype>
        </method>
        <method>
            <name>Invalidate2</name>
            <comment></comment>
            <returntype>void</returntype>
            <parameter>
                <name>arg0</name>
                <type>android.graphics.Rect</type>
            </parameter>
        </method>
        <method>
            <name>IsInitialized</name>
            <comment></comment>
            <returntype>boolean</returntype>
        </method>
        <method>
            <name>SetColorRipple</name>
            <comment></comment>
            <returntype>void</returntype>
            <parameter>
                <name>color</name>
                <type>int</type>
            </parameter>
        </method>
        <method>
            <name>Initialize</name>
            <comment></comment>
            <returntype>void</returntype>
            <parameter>
                <name>bA</name>
                <type>anywheresoftware.b4a.BA</type>
            </parameter>
            <parameter>
                <name>EventName</name>
                <type>java.lang.String</type>
            </parameter>
        </method>
        <method>
            <name>SetImageDrawable</name>
            <comment></comment>
            <returntype>void</returntype>
            <parameter>
                <name>icon</name>
                <type>android.graphics.drawable.Drawable</type>
            </parameter>
        </method>
        <method>
            <name>HasShadow</name>
            <comment></comment>
            <returntype>boolean</returntype>
        </method>
        <method>
            <name>Show</name>
            <comment></comment>
            <returntype>void</returntype>
        </method>
        <method>
            <name>Show2</name>
            <comment></comment>
            <returntype>void</returntype>
            <parameter>
                <name>animate</name>
                <type>boolean</type>
            </parameter>
        </method>
        <method>
            <name>SetType</name>
            <comment></comment>
            <returntype>void</returntype>
            <parameter>
                <name>type</name>
                <type>int</type>
            </parameter>
        </method>
        <method>
            <name>SetLayout</name>
            <comment></comment>
            <returntype>void</returntype>
            <parameter>
                <name>arg0</name>
                <type Pixel="true">int</type>
            </parameter>
            <parameter>
                <name>arg1</name>
                <type Pixel="true">int</type>
            </parameter>
            <parameter>
                <name>arg2</name>
                <type Pixel="true">int</type>
            </parameter>
            <parameter>
                <name>arg3</name>
                <type Pixel="true">int</type>
            </parameter>
        </method>
        <method>
            <name>Invalidate</name>
            <comment></comment>
            <returntype>void</returntype>
        </method>
        <method>
            <name>AddToParent</name>
            <comment></comment>
            <returntype>void</returntype>
            <parameter>
                <name>viewGroup</name>
                <type>android.view.ViewGroup</type>
            </parameter>
            <parameter>
                <name>n</name>
                <type Pixel="true">int</type>
            </parameter>
            <parameter>
                <name>n2</name>
                <type Pixel="true">int</type>
            </parameter>
            <parameter>
                <name>n3</name>
                <type Pixel="true">int</type>
            </parameter>
            <parameter>
                <name>n4</name>
                <type Pixel="true">int</type>
            </parameter>
        </method>
        <method>
            <name>DesignerCreateView</name>
            <comment></comment>
            <returntype>void</returntype>
            <parameter>
                <name>panelWrapper</name>
                <type>anywheresoftware.b4a.objects.PanelWrapper</type>
            </parameter>
            <parameter>
                <name>labelWrapper</name>
                <type>anywheresoftware.b4a.objects.LabelWrapper</type>
            </parameter>
            <parameter>
                <name>map</name>
                <type>anywheresoftware.b4a.objects.collections.Map</type>
            </parameter>
        </method>
        <method>
            <name>SetColorAnimated</name>
            <comment></comment>
            <returntype>void</returntype>
            <parameter>
                <name>arg0</name>
                <type>int</type>
            </parameter>
            <parameter>
                <name>arg1</name>
                <type>int</type>
            </parameter>
            <parameter>
                <name>arg2</name>
                <type>int</type>
            </parameter>
        </method>
        <method>
            <name>SetLayoutAnimated</name>
            <comment></comment>
            <returntype>void</returntype>
            <parameter>
                <name>arg0</name>
                <type>int</type>
            </parameter>
            <parameter>
                <name>arg1</name>
                <type Pixel="true">int</type>
            </parameter>
            <parameter>
                <name>arg2</name>
                <type Pixel="true">int</type>
            </parameter>
            <parameter>
                <name>arg3</name>
                <type Pixel="true">int</type>
            </parameter>
            <parameter>
                <name>arg4</name>
                <type Pixel="true">int</type>
            </parameter>
        </method>
        <method>
            <name>SetVisibleAnimated</name>
            <comment></comment>
            <returntype>void</returntype>
            <parameter>
                <name>arg0</name>
                <type>int</type>
            </parameter>
            <parameter>
                <name>arg1</name>
                <type>boolean</type>
            </parameter>
        </method>
        <method>
            <name>SendToBack</name>
            <comment></comment>
            <returntype>void</returntype>
        </method>
        <property>
            <name>Enabled</name>
            <returntype>boolean</returntype>
            <parameter>
                <name>arg0</name>
                <type>boolean</type>
            </parameter>
            <comment></comment>
        </property>
        <property>
            <name>Parent</name>
            <returntype>java.lang.Object</returntype>
            <comment></comment>
        </property>
        <property>
            <name>Visible</name>
            <returntype>boolean</returntype>
            <parameter>
                <name>arg0</name>
                <type>boolean</type>
            </parameter>
            <comment></comment>
        </property>
        <property>
            <name>Tag</name>
            <returntype>java.lang.Object</returntype>
            <parameter>
                <name>arg0</name>
                <type>java.lang.Object</type>
            </parameter>
            <comment></comment>
        </property>
        <property>
            <name>Height</name>
            <returntype>int</returntype>
            <parameter>
                <name>arg0</name>
                <type Pixel="true">int</type>
            </parameter>
            <comment></comment>
        </property>
        <property>
            <name>Background</name>
            <returntype>android.graphics.drawable.Drawable</returntype>
            <parameter>
                <name>arg0</name>
                <type>android.graphics.drawable.Drawable</type>
            </parameter>
            <comment></comment>
        </property>
        <property>
            <name>Width</name>
            <returntype>int</returntype>
            <parameter>
                <name>arg0</name>
                <type Pixel="true">int</type>
            </parameter>
            <comment></comment>
        </property>
        <property>
            <name>Color</name>
            <parameter>
                <name>arg0</name>
                <type>int</type>
            </parameter>
            <comment></comment>
        </property>
        <field>
            <name>TYPE_MINI</name>
            <comment></comment>
            <returntype>int</returntype>
        </field>
        <field>
            <name>ba</name>
            <comment></comment>
            <returntype>anywheresoftware.b4a.BA</returntype>
        </field>
        <field>
            <name>TYPE_NORMAL</name>
            <comment></comment>
            <returntype>int</returntype>
        </field>
    </class>
    <version>2.02</version>
    <author>Mohsen Soltaniyan</author>
    <dependsOn>android-support-v4</dependsOn>
    <dependsOn>android-support-v7-appcompat</dependsOn>
    <dependsOn>NineOldAndroid-2.4.0</dependsOn>
    <dependsOn>android-support-v7-recyclerview</dependsOn>
</root>
