<?xml version="1.0" encoding="UTF-8"?>
<root>
    <doclet-version-NOT-library-version>1.01</doclet-version-NOT-library-version>
    <class>
        <name>esolutions4you.B4A.moclocationprovider.moclocationprovider</name>
        <shortname>moclocationprovider</shortname>
        <owner>process</owner>
        <permission>android.permission.ACCESS_MOCK_LOCATION</permission>
        <permission>android.permission.ACCESS_FINE_LOCATION</permission>
        <permission>android.permission.ACCESS_COARSE_LOCATION</permission>
        <method>
            <name>publishMockLocation</name>
            <comment></comment>
            <returntype>void</returntype>
            <parameter>
                <name>latitude</name>
                <type>java.lang.String</type>
            </parameter>
            <parameter>
                <name>ns</name>
                <type>java.lang.String</type>
            </parameter>
            <parameter>
                <name>longitude</name>
                <type>java.lang.String</type>
            </parameter>
            <parameter>
                <name>we</name>
                <type>java.lang.String</type>
            </parameter>
            <parameter>
                <name>altitude</name>
                <type>double</type>
            </parameter>
            <parameter>
                <name>speed</name>
                <type>float</type>
            </parameter>
            <parameter>
                <name>bearing</name>
                <type>float</type>
            </parameter>
            <parameter>
                <name>accuracy</name>
                <type>float</type>
            </parameter>
            <parameter>
                <name>ctx</name>
                <type>android.content.Context</type>
            </parameter>
        </method>
        <method>
            <name>enableMockProvider</name>
            <comment></comment>
            <returntype>void</returntype>
            <parameter>
                <name>ctx</name>
                <type>android.content.Context</type>
            </parameter>
        </method>
        <method>
            <name>disableMockProvider</name>
            <comment></comment>
            <returntype>void</returntype>
            <parameter>
                <name>ctx</name>
                <type>android.content.Context</type>
            </parameter>
        </method>
    </class>
    <version>1.0</version>
    <author>bitstra</author>
</root>
